README.md
setup.cfg
setup.py
Empiric/Experiment.py
Empiric/Mode.py
Empiric/Register.py
Empiric/Statistics.py
Empiric/__info__.py
Empiric/__init__.py
Empiric.egg-info/PKG-INFO
Empiric.egg-info/SOURCES.txt
Empiric.egg-info/dependency_links.txt
Empiric.egg-info/requires.txt
Empiric.egg-info/top_level.txt
Empiric/Pages/Page.py
Empiric/Pages/PageAccessCode.py
Empiric/Pages/PageFinal.py
Empiric/Pages/PageInfo.py
Empiric/Pages/PageMap.py
Empiric/Pages/PageQuestionnaire.py
Empiric/Pages/__init__.py
Empiric/files/_PageExample.py
Empiric/files/_pageExample.html
Empiric/files/package.json
Empiric/files/package2.json
Empiric/files/yarn.lock
Empiric/files/yarnrc
Empiric/files/yarnrc2
Empiric/internal/AccessCodes.py
Empiric/internal/Authenticate.py
Empiric/internal/GeneralSettings.py
Empiric/internal/ManuscriptMemory.py
Empiric/internal/Print.py
Empiric/internal/Statistics.py
Empiric/internal/StatisticsTools.py
Empiric/internal/Step.py
Empiric/internal/__init__.py
Empiric/templates/html.html
Empiric/templates/login.html
Empiric/templates/page.html
Empiric/templates/pageAccessCode.html
Empiric/templates/pageFinal.html
Empiric/templates/pageInfo.html
Empiric/templates/pageMap.html
Empiric/templates/pageQuestionnaire.html
Empiric/templates/statistics.html