Metadata-Version: 1.2
Name: Empiric
Version: 0.0.2
Summary: Empiric!, an easy-to-use framework to conduct empirical experiments, with a particular focus on geospatial data perception and contribution
Home-page: https://github.com/mocnik-science/empiric
Author: Franz-Benjamin Mocnik
Author-email: mail@mocnik-science.net
License: GPL-3
Keywords: empirical experiment,map,framework,testing,psychology,cognition
Platform: UNKNOWN
Classifier: Development Status :: 4 - Beta
Classifier: Programming Language :: Python :: 3
Requires-Python: >=3.6
